ocr_toolkits/__init__.py
ocr_toolkits/change_files_ext.py
ocr_toolkits/delete_files_ext.py
ocr_toolkits/move_files_ext.py
ocr_toolkits/rename_files_ext.py
ocr_toolkits/resize.py
ocr_toolkits/synth_data.py
ocr_toolkits/utils.py
ocr_toolkits/postprocess/__init__.py
ocr_toolkits-0.0.3.dist-info/LICENSE.txt
ocr_toolkits-0.0.3.dist-info/METADATA
ocr_toolkits-0.0.3.dist-info/WHEEL
ocr_toolkits-0.0.3.dist-info/top_level.txt
ocr_toolkits-0.0.3.dist-info/RECORD
