Metadata-Version: 2.1
Name: ocr-toolkits
Version: 0.0.3
Summary: Ocr_tools is a Python library that generates synthetic images containing Khmer text and other important toolbox
Home-page: https://github.com/MetythornPenn/ocr-toolkits.git
Author: Metythorn Penn
Author-email: metythorn@gmail.com
License: Apache Software License 2.0
Keywords: ocr-toolkits
Platform: UNKNOWN
Classifier: Natural Language :: English
Classifier: License :: OSI Approved :: Apache Software License
Classifier: Operating System :: OS Independent
Classifier: Programming Language :: Python :: 3
Requires-Dist: Pillow
Requires-Dist: jellyfish
Requires-Dist: opencv-python
Requires-Dist: numpy
